mark_toc/__init__.py
mark_toc/__main__.py
mark_toc/argparsing.py
mark_toc/cli.py
mark_toc/completion.py
mark_toc/iofile.py
mark_toc/mdfile.py
mark_toc-0.5.0.dist-info/METADATA
mark_toc-0.5.0.dist-info/WHEEL
mark_toc-0.5.0.dist-info/entry_points.txt
mark_toc-0.5.0.dist-info/licenses/LICENSE
mark_toc-0.5.0.dist-info/RECORD
