Metadata-Version: 2.3
Name: mark-toc
Version: 0.5.0
Summary: Generate table of contents in Markdown files based on headings
Project-URL: Repository, https://github.com/jmknoble/mark-toc
Author-email: jmknoble <jmknoble@pobox.com>
License: MIT License
Keywords: cli,development,markdown,pre-commit,table of contents,text
Classifier: Development Status :: 4 - Beta
Classifier: Environment :: Console
Classifier: Environment :: Other Environment
Classifier: Intended Audience :: Developers
Classifier: Intended Audience :: Information Technology
Classifier: License :: OSI Approved :: MIT License
Classifier: Natural Language :: English
Classifier: Operating System :: OS Independent
Classifier: Programming Language :: Python :: 3
Classifier: Programming Language :: Python :: 3.10
Classifier: Topic :: Software Development
Classifier: Topic :: Utilities
Requires-Python: >=3.10
Requires-Dist: argcomplete>=1.12.3
